label_wrapper/__init__.py
label_wrapper/core.py
label_wrapper/io.py
label_wrapper/via-2.0.6.html
label_wrapper-0.1.2.dist-info/LICENSE
label_wrapper-0.1.2.dist-info/METADATA
label_wrapper-0.1.2.dist-info/WHEEL
label_wrapper-0.1.2.dist-info/top_level.txt
label_wrapper-0.1.2.dist-info/RECORD
