Metadata-Version: 2.1
Name: label-wrapper
Version: 0.1.2
Summary: User friendly image bootstraping framework.
Home-page: https://github.com/rok/label-wrapper
Author: Rok Mihevc
Author-email: me@rok.dev
License: MIT
Platform: UNKNOWN
Classifier: License :: OSI Approved :: MIT License
Classifier: Programming Language :: Python
Classifier: Programming Language :: Python :: 3
Classifier: Programming Language :: Python :: 3.6
Classifier: Programming Language :: Python :: Implementation :: CPython
Classifier: Programming Language :: Python :: Implementation :: PyPy
Requires-Python: >=3.6.0
Requires-Dist: attr
Requires-Dist: jinja2
Requires-Dist: numpy
Requires-Dist: scikit-image
Requires-Dist: tensorflow
